pygoval-0.1.0.dist-info/METADATA
pygoval-0.1.0.dist-info/WHEEL
pygoval/__init__.py
pygoval/base36.py
pygoval/channel.py
pygoval/client.py
pygoval/exceptions.py
pygoval/proto/api_pb2.py
pygoval/proto/api_pb2.pyi
pygoval-0.1.0.dist-info/RECORD
